Metadata-Version: 2.1
Name: ima-demo
Version: 0.0.1
Summary: PyPI Tutorial
Home-page: https://github.com/
Author: mach
Author-email: machheji@gmail.com
Classifier: Programming Language :: Python :: 3
Classifier: License :: OSI Approved :: MIT License
Classifier: Operating System :: OS Independent
Requires-Python: >=3
